store/__init__.py
store/database.py
store/parser.py
store/contrib/__init__.py
store/contrib/factory/__init__.py
store/contrib/factory/db.py
store-2020.2.9.dist-info/METADATA
store-2020.2.9.dist-info/WHEEL
store-2020.2.9.dist-info/top_level.txt
store-2020.2.9.dist-info/RECORD
